MANIFEST.in
setup.py
src/archetypes/__init__.py
src/archetypes.searchwidget.egg-info/PKG-INFO
src/archetypes.searchwidget.egg-info/SOURCES.txt
src/archetypes.searchwidget.egg-info/dependency_links.txt
src/archetypes.searchwidget.egg-info/entry_points.txt
src/archetypes.searchwidget.egg-info/namespace_packages.txt
src/archetypes.searchwidget.egg-info/not-zip-safe
src/archetypes.searchwidget.egg-info/requires.txt
src/archetypes.searchwidget.egg-info/top_level.txt
src/archetypes/searchwidget/HISTORY.txt
src/archetypes/searchwidget/README.txt
src/archetypes/searchwidget/__init__.py
src/archetypes/searchwidget/configure.zcml
src/archetypes/searchwidget/demo.py
src/archetypes/searchwidget/interfaces.py
src/archetypes/searchwidget/search.py
src/archetypes/searchwidget/search_images.pt
src/archetypes/searchwidget/search_results.pt
src/archetypes/searchwidget/searchresult_image.pt
src/archetypes/searchwidget/tests.py
src/archetypes/searchwidget/vocabulary.py
src/archetypes/searchwidget/widget.py
src/archetypes/searchwidget/profiles/default/cssregistry.xml
src/archetypes/searchwidget/profiles/default/jsregistry.xml
src/archetypes/searchwidget/profiles/default/metadata.xml
src/archetypes/searchwidget/profiles/default/skins.xml
src/archetypes/searchwidget/profiles/demo/factorytool.xml
src/archetypes/searchwidget/profiles/demo/types.xml
src/archetypes/searchwidget/profiles/demo/types/SearchWidgetDemo.xml
src/archetypes/searchwidget/skins/archetypes.searchwidget/searchwidget.pt
src/archetypes/searchwidget/style/custom.css
src/archetypes/searchwidget/style/images/cccccc_40x100_textures_03_highlight_soft_75.png
src/archetypes/searchwidget/style/smoothness/demo.html
src/archetypes/searchwidget/style/smoothness/ui.accordion.css
src/archetypes/searchwidget/style/smoothness/ui.all.css
src/archetypes/searchwidget/style/smoothness/ui.allplugins.css
src/archetypes/searchwidget/style/smoothness/ui.core.css
src/archetypes/searchwidget/style/smoothness/ui.datepicker.css
src/archetypes/searchwidget/style/smoothness/ui.dialog.css
src/archetypes/searchwidget/style/smoothness/ui.progressbar.css
src/archetypes/searchwidget/style/smoothness/ui.resizable.css
src/archetypes/searchwidget/style/smoothness/ui.slider.css
src/archetypes/searchwidget/style/smoothness/ui.tabs.css
src/archetypes/searchwidget/style/smoothness/ui.theme.css
