Metadata-Version: 1.0
Name: archetypes.searchwidget
Version: 0.1.1
Summary: UNKNOWN
Home-page: http://svn.plone.org/svn/archetypes/MoreiFieldAndWidgets
Author: Rok Garbas
Author-email: rok.garbas@gmail.com
License: GPL
Keywords: plone archtypes widget search reference
Platform: UNKNOWN
Classifier: Framework :: Plone
Classifier: Programming Language :: Python
Classifier: Topic :: Software Development :: Libraries :: Python Modules
